{
  "title": "Uygulamalı Eğitimler Koordinatörlüğü - Kamu ve Özel Sektör İş Birlikleri",
  "url": "https://www.esenyurt.edu.tr/icerik/3839-uygulamali-egitimler-koordinatorlugu-kamu-ve-ozel-sektor-is-birlikleri",
  "content": "Uygulamalı Eğitimler Koordinatörlüğü - Kamu ve Özel Sektör İş Birlikleri\n\nBu içerik 19/12/2025 tarihinde güncellenmiştir.",
  "language": "tr",
  "content_type": "academic",
  "timestamp": "2026-04-12T18:51:44.748763Z",
  "university": "Istanbul Esenyurt University",
  "source_hash": "d6b627479e3e8c04549eff62d16dec60ab9ec162dcf6a2a48b70c41ff1322b69"
}