{
  "title": "Üniversitemiz İle Daaru Salaam Üniversitesi Arasında Akademik İş Birliği Protokolü İmzalandı",
  "url": "https://www.esenyurt.edu.tr/haber/1328-universitemiz-ile-daaru-salaam-universitesi-arasinda-akademik-is-birligi-protokolu-imzalandi",
  "content": "Üniversitemiz İle Daaru Salaam Üniversitesi Arasında Akademik İş Birliği Protokolü İmzalandı\n\nÜniversitemiz, Somali Daaru Salaam Üniversitesi'nden gelen heyete ev sahipliği yaptı. Üniversite Rektörü Dr. Osman Mohamed Hassan, beraberindeki bir heyetle Rektörümüz Prof. Dr. Süleyman Özdemir'i ziyaret etti. Ziyarette, iki üniversite arasında akademik iş birliği, öğrenci ve öğretim üyesi değişimi, vb. konularda bir işbirliği protokolü imzalandı. Bu iş birliğinin, iki üniversite için de hayırlı ve verimli olmasını temenni ediyoruz.\n\nZiyarette, misafir heyete TASİP (Tüm Afrika Sanayici ve İş İnsanları Platformu) Disiplin Kurulu Başkanı Neslihan Tanır da eşlik etti. Üniversitemiz Rektör Yardımcısı Prof. Dr. Dinçer Atlı, Lisansüstü Eğitim Enstitüsü Müdür Yardımcısı Dr. Öğrt. Üyesi Zekeriya Şahin, Erasmus Koordinatörü Arş. Gör. Merve Sevinç Sakar da ziyarette hazır bulundu.\n\nBu içerik 14/01/2026 tarihinde güncellenmiştir.",
  "language": "tr",
  "content_type": "news",
  "timestamp": "2026-04-12T18:52:00.633416Z",
  "university": "Istanbul Esenyurt University",
  "source_hash": "c6462d2894099ade6377eaa955302d47bd11e2ff0ca6a8a42f4945578cf257b5"
}