{
  "title": "Misyon Vizyon",
  "url": "https://www.galata.edu.tr/tr/muhendislik-ve-doga-bilimleri-fakultesi/akademi-detay-sayfa/muhendislik-ve-doga-bilimleri-fakultesi-misyon-vizyon",
  "content": "Bilgisayar Mühendisliği\n\nAnasayfa\n\n/\n\nBilgisayar Mühendisliği\n\n/\n\nMisyon Vizyon\n\nBilgisayar Mühendisliği\n\nHakkımızda\n\nMisyon Vizyon\n\nAkademik Kadro\n\nEğitim\n\nMisyon Vizyon",
  "language": "en",
  "content_type": "academic",
  "timestamp": "2026-04-12T23:17:11.801155Z",
  "university": "Istanbul Galata University",
  "source_hash": "ea3215117c80fe5248f7ff80d470b700771392df9c28b9f5d57e5662eb2b0598"
}