{
  "title": "Dekanlık",
  "url": "https://www.galata.edu.tr/tr/muhendislik-fakultesi/akademi-detay-sayfa/muhendislik-dekanlik",
  "content": "YÖNETİM\n\nAnasayfa\n\n/\n\nYÖNETİM\n\n/\n\nDekanlık\n\nYÖNETİM\n\nDekanlık\n\nFakülte Kurulu\n\nDekanlık\n\nDekan V.\n\nProf. Dr. Şeyma AYDINOĞLU\n\nFakülte Sekreteri\n\nHandan Kurtuluş\n\nhandan.kurtulus@galata.edu.tr",
  "language": "en",
  "content_type": "academic",
  "timestamp": "2026-04-12T23:13:57.515113Z",
  "university": "Istanbul Galata University",
  "source_hash": "ab7b7753d6cb7999939d5d0895e9356618a477bcba517f377a5b832e8e4f6239"
}