{
  "title": "KADİR HAS ÜNİVERSİTESİ’NDEN PROF. DR. DİKMEN GÜRÜN’E EMERİTUS UNVANI - Kadir Has Üniversitesi",
  "url": "https://www.khas.edu.tr/rtc/akademisyenlerimiz/",
  "content": "İçeriğe geç\n\nAKADEMİSYENLERİMİZ\n\nBÖLÜM\n\nBaşarılarımız\n\nHakkımızda\n\nEĞİTİM\n\nLisans Programı\n\nStaj Yönergesi\n\nDoktora Programı\n\nRTS STÜDYOSU\n\nARAŞTIRMA\n\nBilimsel Projeler\n\nBilimsel Yayınlar\n\nAraştırma Grupları\n\nKONFERANS\n\nMyKHAS\n\nSwitch to English Website\n\nAra\n\nATİLLA GİRAY\n\nBursiyer (L)\n\nMELİS BEHLİL\n\nProf. Dr.\n\nBÜLENT DİKEN\n\nProf. Dr.\n\nELİF AKÇALI\n\nDoç. Dr.\n\nDEFNE TÜZÜN\n\nÖğr. Gör. Dr.\n\nYİĞİT CAN AKÇELİK\n\nÖğr. Gör.\n\nUFUK ÇAVUŞ\n\nÖğr. Gör.\n\nPELİN ESMER\n\nÖğr. Gör.\n\nGÖKSENİN GÖKSEL\n\nÖğr. Gör.\n\nTUVANA SİMİN GÜNAY\n\nÖğr. Gör.\n\nKAĞAN KERİMOĞLU\n\nÖğr. Gör.\n\nRAMİN MATİN\n\nÖğr. Gör.\n\nÖğr. Gör.\n\nÖğr. Gör.\n\nHALİL DENİZ TORTUM\n\nÖğr. Gör.\n\nAraş. Gör.\n\nProf. Dr.\n\nDoç. Dr.\n\nÖğretim Görevlisi\n\nAraştırma Görevlisi\n\nHızlı Arama\n\nİletişim Bilgileri\n\nTelefon:\n\n+90 (212) 533 65 32\n\nFax:\n\n+90 (212) 631\n                            91 50\n\nE-Posta:\n\n[email protected]\n\nAdres:",
  "language": "en",
  "content_type": "academic",
  "timestamp": "2026-04-12T18:34:32.553198Z",
  "university": "Kadir Has University",
  "source_hash": "4557bb68dfbd246ba2f36ee2909f1743a2d529087369b6458bed7cf48dd07096"
}