{
  "title": "rtc-TV Series: A Comparative Perspective &#From Geopolitics to Geocriticism Serbia and Turkey",
  "url": "https://www.khas.edu.tr/en/rtc-tv-series-a-comparative-perspective-from-geopolitics-to-geocriticism-serbia-and-turkey/",
  "content": "THE DEPARTMENT\n\nAbout Us\n\nOur Achievements\n\nPartners & Collaborations\n\nAcademic Staff\n\nEDUCATİON\n\nUndergraduate Program\n\nMA Program\n\nPhD Program\n\nRADIO, TELEVISION AND CINEMA STUDIO\n\nResearch Groups\n\nRESEARCH\n\nCONFERENCE\n\nMyKHAS\n\nTürkçe\n\nrtc-TV Series: A Comparative Perspective &#From Geopolitics to Geocriticism Serbia and Turkey\n\nCoordinators\n\nProf. Dr. Nevena Dakovic (Serbia)\n\nProject Team\n\nTurkey Research Group\n\nAssoc. Prof. Melis Behlil\n\nAssoc. Prof. Levent Soysal\n\nDr. Hilmi Bengi\n\nAliye Atalay\n\nSelçuk Yavuzkanat, Ministry of Culture and Tourism, Directorate of Cinema, Deputy Director/Advisor\n\nSerbia Research Group\n\nDoç. Dr. Aleksander S. Janković, Project Member\n\nDoç. Dr. Ana Martinoli, Project Member\n\nDoç. Dr. Aleksandra Milovanović, Project Member\n\nArea of Research​\n\nThe project examines the geopolitics of the Balkan region and the geopolitical relations of Serbia and Turkey. Serbia and Turkey, with shared geographies, histories, and cultures in the Balkans, will be approached in this study based on the emotions embedded in TV series and the referentiality to real and imaginary places that were read through them.\n\nThe focus is on the case studies of four genre pairs from Turkey and Serbia. The national imaginary and cultural imagination that is constructed, changed, and transferred through the drama contents in both countries and its reception; the national and transnational identities, representation of the past and the everyday life; in general, how the geopolitics of TV series work articulated in the emerging notion of geocriticism (Maoz Azaryanh & Kenneth E. Foote: 2008; Westphal 2011; M.L. Ryan: 2012).\n\nThe project is supported by TÜBİTAK-Serbia Ministry of Education, Science and Technological Development (MoESTD) Bilateral Cooperation Program.\n\nVisit Website\n\nTwitter\n\nInstagram\n\nQuick Search\n\nThrough this form, you can access news, announcements, faculties and departments, base scores, our academic staff and administrative personnel, and their internal phone numbers.\n\nContact Information\n\nPhone:\n\n+90 (212) 533 65 32\n\nFax:\n\n+90 (212) 631\n                            91 50\n\nEmail:\n\n[email protected]\n\nAddress:\n\nCibali Mah. Kadir\n                            Has Cad. 34083 Fatih, İstanbul",
  "language": "en",
  "content_type": "academic",
  "timestamp": "2026-04-12T18:45:53.044984Z",
  "university": "Kadir Has University",
  "source_hash": "3ccdc2958c88c25b937c441d1948a09bb46fd0e71850c096af0ff95b3287618f"
}