{
  "title": "Faculty of Engineering and Natural Sciences",
  "url": "https://www.okan.edu.tr/en/muhendislik/page/8546/accreditation-and-continuous-improvement/",
  "content": "Okan Homepage\n\nEducation\n\nAcademic Units\n\nFaculties\n\nDepartments\n\nMENU\n\n2022 - 2027\n\n2018 - 2019\n\nen\n\ntr",
  "language": "tr",
  "content_type": "academic",
  "timestamp": "2026-04-12T19:30:10.395499Z",
  "university": "Istanbul Okan University",
  "source_hash": "7a97e25cf272db5164078cd2fadf2af3a1bebb31238e38cea3894eede19a294f"
}