{
  "title": "Sağlık Bilimleri Fakültesi",
  "url": "https://www.okan.edu.tr/sbf/bolum/52/hemsirelik/",
  "content": "Sağlık Bilimleri Fakültesi\n\nHemşirelik\n\nOkan Anasayfa\n\nEğitim\n\nAkademik Birimler\n\nFakülteler\n\nSağlık Bilimleri Fakültesi\n\nBölümler\n\nHemşirelik\n\nMENU\n\nBölümümüz; bireyin, ailenin ve toplumun sağlığını koruma, geliştirme ve hastalık halinde iyileştirme amacına yönelik hemşirelik hizmetlerini planlayan, örgütleyen, uygulayan, değerlendiren ve bu hizmetleri yerine getirecek kişileri eğiten, araştırmacı, danışman, yönetici olarak görev alacak uluslararası standart ve etik kodları kullanan disiplinler arası ekip çalışması yapan, insanlığa ve ülkesine karşı sorumluluklarını bilen hemşireler yetiştirmeyi amaçlamaktadır.\n\nKamu ve Özel sektör sağlık kurumlarında staj yapma imkanına sahip olan öğrencilerimiz, teorik ve pratik eğitimlerini çoğunluğu sağlık sektöründen gelme, kendisini bu sektörde kanıtlamış olan öğretim üyelerinden almaktadırlar.\n\nSağlık Bakanlığı verilerine göre, Türkiye'de hemşire gereksinimi oldukça fazladır. Bunun yanında yurtdışında istihdam edilmek üzere ve son yıllarda ülkemizde sağlık turizminin gelişmesi ile yabancı dil bilen hemşire taleplerinde artış gözlenmektedir. Öğrencilerimizin mezun oldukları zaman her alanda söz sahibi olabilmeleri için, öğrenimleri sırasında iki yabancı dili öğrenmeleri sağlanmaktadır.\n\nen\n\ntr",
  "language": "tr",
  "content_type": "academic",
  "timestamp": "2026-04-12T19:26:08.851219Z",
  "university": "Istanbul Okan University",
  "source_hash": "01dce10f48794b82010af763a27ad593027494910104c85c78cec9d5e0e718f0"
}