{
  "title": "HABERLER",
  "url": "https://www.yeniyuzyil.edu.tr/haber-detay/sahne-sanatlari-bolumunden-cok-katmanli-gosteri-etkinligi",
  "content": "Ana Sayfa\n\n>\n\nHaberler\n\n>\n\nSahne Sanatları Bölümünden Çok Katmanlı Gösteri Etkinliği\n\nHABERLER\n\nGeri Dön\n\nSahne Sanatları Bölümünden Çok Katmanlı Gösteri Etkinliği\n\nYayınlanma Tarihi:\n\n9.4.2026\n\nSahne Sanatları Bölümünden Çok Katmanlı Gösteri Etkinliği\n\n27 Mart 2026 tarihinde saat 13:00’te, Güzel Sanatlar Fakültesi Sahne Sanatları Bölümü tarafından Alev Ofluoğlu Konferans Salonunda düzenlenen ve tüm T.C. İstanbul Yeni Yüzyıl Üniversitesi öğrencilerine açık olan “Reji / Şiir Dinletisi / Öğrenci Sahnelemeleri” etkinliği, Dr. Öğr. Üy. Ülkü Şahin ve Dr. Öğr. Üy. Özgür Yetkinoğlu’nun liderliğinde gerçekleştirildi.\n\nGüzel Sanatlar Fakültesi akademik ve idari kadrosu ile Sahne Sanatları Bölümü öğrencilerinin katılım gösterdiği etkinliğin ilk bölümünde, ulusal ve uluslararası Dünya Tiyatro Günü bildirileri okundu. Etkinliğin sunuculuğunu Sahne Sanatları Bölümü 4. sınıf öğrencileri Berat Yıldız ve Çağla Namal üstlendi.\n\nEtkinlikte, öğrencilerin sahneleme, reji ve performans süreçlerini deneyimlemelerine yönelik çalışmalar sunulurken, akademisyenlerin yönetmenlik ve süpervizörlük desteğiyle öğrencilerin sanatsal üretimlerinin geliştirilmesi hedeflendi. Şiir dinletisi ile sahneleme çalışmalarının bir araya getirildiği etkinlikte çok katmanlı bir performans deneyimi oluşturuldu.\n\nEtkinlik kapsamında öğrenciler tarafından hazırlanan şiir dinletisi, reji çalışmaları ve sahnelemeler, akademisyenlerin yönetmenlik ve süpervizörlüğünde sahnelendi. Süreç boyunca öğrencilerin sahneleme pratikleri desteklenirken, performansların oluşturulması ve geliştirilmesi aşamalarında akademik rehberlik sağlandı.\n\nGerçekleştirilen etkinlikle öğrencilerin hem bireysel hem de kolektif üretim süreçlerini deneyimlemelerine olanak tanınması amaçlandı. Etkinlik, gerçekleştirilen performansların ardından sona erdi.\n\nTüm Haberler Arşivi\n\nSon Yayınlananlar\n\nDeniz Ticareti Hukuku Kulübü Faaliyetlerine Başladı\n\n10.4.2026\n\nMoleküler Biyoloji ve Genetik Bölümü FEDEK Tarafından 5 Yıl Akredite Edildi\n\n10.4.2026\n\nBasketbol Takımımız Namağlup Çeyrek Finalde!\n\n9.4.2026\n\nSahne Sanatları Bölümünden Çok Katmanlı Gösteri Etkinliği\n\n9.4.2026\n\nSahne Sanatları Bölümünden Dünya Tiyatro Günü’ne Özel Müzikal Etkinlik\n\n9.4.2026\n\nİlginizi Çekebilir\n\nDeniz Ticareti Hukuku Kulübü Faaliyetlerine Başladı\n\n10.4.2026\n\nMoleküler Biyoloji ve Genetik Bölümü FEDEK Tarafından 5 Yıl Akredite Edildi\n\n10.4.2026\n\nBasketbol Takımımız Namağlup Çeyrek Finalde!\n\n9.4.2026\n\nSahne Sanatları Bölümünden Çok Katmanlı Gösteri Etkinliği\n\n9.4.2026\n\nSahne Sanatları Bölümünden Dünya Tiyatro Günü’ne Özel Müzikal Etkinlik\n\n9.4.2026",
  "language": "tr",
  "content_type": "news",
  "timestamp": "2026-04-12T21:17:15.678819Z",
  "university": "Istanbul Yeni Yüzyıl University",
  "source_hash": "8867146b42f64452e5ff79ca041d9824b725f15382b99889574139f5435ac4bb"
}