{
  "title": "Announcements",
  "url": "https://www.dogus.edu.tr/en/announcements/-in-category/categories/announcements/archive/2020",
  "content": "Announcements\n\nCategories\n\n2026\n\n2025\n\n2024\n\n2023\n\n2022\n\n2021\n\n2020\n\n2019\n\n2018\n\n2017\n\n2016\n\nAnnouncements\n\nJul\n\n10\n\nMar\n\n15\n\nJan\n\n21\n\nPaylaş",
  "language": "tr",
  "content_type": "news",
  "timestamp": "2026-04-12T21:38:32.563502Z",
  "university": "Doğuş University",
  "source_hash": "b2af44b22b57c6e3ba04981880b1a9b4047afd1301c698cbb092f8a07f43f2b7"
}