{
  "title": "ADMISSION TO UNDERGRADUATE PROGRAMS",
  "url": "https://www.khas.edu.tr/admission-to-undergraduate-programs-2/",
  "content": "Skip to content\n\nHOMEPAGE\n\nADMISSION\n\nPROGRAMS\n\nUndergraduate Programs\n\nAcademic Master Degrees\n\nTuition Fee\n\nBrochure\n\nPARENTS CLUB\n\nLiving in Istanbul\n\nOur Campus\n\nStudent Clubs\n\nCONTACT\n\nAPPLY NOW\n\nTürkçe\n\nADMISSION TO UNDERGRADUATE PROGRAMS\n\nApplication Requirements\n\nRegistration\n\nQuick Search\n\nContact Information\n\nPhone:\n\n+90 (212) 533 65 32\n\nFax:\n\n+90 (212) 631\n                            91 50\n\nEmail:\n\n[email protected]\n\nAddress:",
  "language": "tr",
  "content_type": "academic",
  "timestamp": "2026-04-12T18:35:36.193729Z",
  "university": "Kadir Has University",
  "source_hash": "ef73e604c16d1bbad2fc365ba443bab69dd5283bc8c09d52109611332d6b9199"
}