{
  "title": "MIS-Publications",
  "url": "https://www.khas.edu.tr/en/mis-publications/",
  "content": "THE DEPARTMENT\n\nAcademic Staff\n\nACADEMIC\n\nMSc in MIS\n\nRESEARCH\n\nPublications\n\nProjects\n\nResearch Centers\n\nPARTNETSHIP\n\nAdvisory Board\n\nInternship\n\nMyKHAS\n\nTürkçe\n\nMIS-Publications\n\nCeylan, O.\n\nhttps://doi.org/10.1007/s00521-020-05062-8\n\nO. Ceylan,\n\nEmmanuel Agullo, Siegfried Cools,\n\nEmrullah Fatih Yetkin,\n\nhttps://doi.org/10.1137/18M122858X\n\nKaradayi, Y.,\n\nAydin, M.N.,\n\nIEEE Access\n\n, vol. 8, pp. 164155-164177, 2020, doi: 10.1109/ACCESS.2020.3022366.\n\nAydin, S.,\n\nApplied Sciences\n\n, 10(13), 4460.\n\nAkdur, G.,\n\nAydin, M. N.,\n\nAydin, S.,\n\n, 175, 105589\n\nKaradayı, Y.,\n\nAydin, M. N.,\n\nÇavur, M.\n\nCavur, M.\n\nIşık Muhittin and\n\nHasan Dag\n\nCeylan, O.\n\nCeylan, O.\n\nTaşkın, G., and\n\nCeylan, O.\n\nÇavur, M.\n\nCeylan O.\n\nDilan E.\n\nDahman M.R.,\n\nDağ H.\n\nAydin M.N.\n\nAydin M.N.\n\nQuick Search\n\nContact Information\n\nPhone:\n\n+90 (212) 533 65 32\n\nFax:\n\n+90 (212) 631\n                            91 50\n\nEmail:\n\n[email protected]\n\nAddress:",
  "language": "tr",
  "content_type": "academic",
  "timestamp": "2026-04-12T18:33:09.648140Z",
  "university": "Kadir Has University",
  "source_hash": "9e9dc3f4081b0c1a217b388be4eea584556d8d18d8fea452de2981137f9cd44a"
}