{
  "title": "Eğitim",
  "url": "https://www.khas.edu.tr/ydy/akademisyenlerimiz/2379/",
  "content": "İçeriğe geç\n\nHAKKIMIZDA\n\nAkademisyenlerimiz\n\nMisyon ve Vizyon\n\nYüksekokul Yönetimi\n\nAKADEMİK PROGRAMLAR\n\nİngilizce Hazırlık Programı (İHP)\n\nModern Diller Programı\n\nÖĞRENCİLER\n\nAkademik Takvim\n\nÖğrenci El Kitabı\n\nKHAS İngilizce Seviye Tespit ve Yeterlilik Sınavı\n\nSıkça Sorulan Sorular\n\nKALİTE GÜVENCESİ\n\nAkreditasyon\n\nİŞ OLANAKLARI\n\nİLETİŞİM\n\nMyKHAS\n\nDr. Öğr. Üyesi\n\nSİBEL KARADAĞ\n\n+90 (212) 533 65 32 /\n\t\t\t\t\t\t\t1626\n\n[email protected]\n\nAcademia\n\nAcademia\n\nORCID\n\nLinkedIn\n\nEğitim\n\nDoktora\n\nKOÇ ÜNİVERSİTESİ\n\nSiyaset Bilimi ve Uluslararası İlişkiler\n\nYüksek Lisans\n\nSosyal Politika\n\nYüksek Lisans\n\nSABANCI ÜNİVERSİTESİ\n\nAvrupa Çalışmaları\n\nLisans\n\nSABANCI ÜNİVERSİTESİ\n\nToplum ve Siyaset Bilimi\n\nAraştırma Alanları\n\nSınır Çalışmaları\n\nSiyasi coğrafya\n\nGöç ve Hareketlilik\n\nSiyaset Sosyolojisi\n\nSosyal Politika\n\nEmek Çalışmaları\n\nSiyaset Felsefesi\n\nİş Deneyimi\n\nDr. Öğr. Üyesi\n\nKadir Has Üniversitesi\n\n2021 /\n\t\t\t\t\t\t\t\t\t\t\t2022\n\nMercator Stiftung-Istanbul Politikalar Merkezi Araştırmacısı\n\nSabancı Üniversitesi\n\n2020 /\n\t\t\t\t\t\t\t\t\t\t\t2021\n\nDoktora Sonrası Araştırmacı\n\nKoç Üniversitesi\n\n2018 /\n\t\t\t\t\t\t\t\t\t\t\t2019\n\nMisafir Araştırmacı\n\nYale Üniversitesi\n\nTümünü Gör\n\nİdari Görevler\n\nGörev Adı\n\nGörev Yeri\n\nBaşlangıç tarihi\n\nBitiş Tarihi\n\n10.10.2024\n\nUluslararası İlişkiler Master ve Doktora Programı Koordinatörü\n\nKadir Has Üniversitesi\n\n22.07.2024\n\n01.09.2022\n\nYayınlar\n\n,\n\nGeopolitics\n\n, (2025) Vol.30, No.3, 1051-1072\n\nDOI:\n\n10.1080/14650045.2024.2347278\n\nKaradağ, Sibel; Tatar, Doruk;\n\n,\n\nGeopolitics\n\n, (2025) Vol.30, No.3, 1051-1072\n\nDOI:\n\n10.1080/14650045.2024.2347278\n\nKaradağ, Sibel;\n\n,\n\nDOI:\n\n10.24241/rcai.2025.140.2.125\n\n,\n\nKaradağ, Sibel;\n\n,\n\nGeopolitics\n\n, (2024)\n\nDOI:\n\ndoi.org/10.1080/14650045.2024.2347278\n\n,\n\nKaradağ, Sibel;\n\nKaradaǧ, Sibel; Sert, Deniz;\n\n,\n\n, (2023) Vol.36, No.3, 449-466\n\nDOI:\n\n10.1093/jrs/fead029\n\nKaradağ, Sibel; İşleyen, Beste ;\n\n,\n\nSecurity Dialogue\n\n, (2023)\n\nDOI:\n\nhttps://doi.org/10.1177/096701062311949\n\nIPC\n\n, (2022)\n\nHorizon 2020 ADMIGOV Final Report\n\n, (2021)\n\nDOI:\n\nhttps://doi.org/10.1080/14650045.2020.1747902\n\n, (2019)\n\nDOI:\n\nDOI:10.1186/s40878-019-0113-y\n\n, (2018) Vol.19, No.3,\n\nDOI:\n\nhttps://doi.org/10.1080/14683849.2018.1454317\n\nProjeler\n\nProje Adı\n\nGörevi\n\nProje Türü\n\nFonlayan Kuruluş\n\nBaşlangıç Tarihi\n\nBitiş Tarihi\n\nYürütücü\n\nUluslararası Proje\n\nCOST\n\n28.09.2023\n\n27.09.2027\n\nYürütücü\n\nUluslararası Proje\n\nDiğer Uluslararası\n\n01.08.2024\n\n01.03.2025\n\nYürütücü\n\nUluslararası Proje\n\nDiğer Uluslararası\n\n01.09.2021\n\n30.04.2022\n\nVerilen Dersler\n\nDers Adı\n\nDers Kodu\n\nDönem\n\nSiyasal Düşünceler Tarihi\n\nPSIR204\n\n2025/26 Bahar\n\nAvrupa’da Göç ve Sınırlar\n\nPSIR464\n\n2025/26 Bahar\n\nSiyaset Sosyolojisi\n\nPSIR217\n\n2025/26 Güz\n\nHareketlilik, Sınırlar ve Teknoloji\n\nPS503\n\n2025/26 Güz\n\nPrep GPT\n\nHızlı Arama\n\nBu form aracılığı ile haberler, duyurular, fakülte ve bölümler, taban puanları, akademisyenlerimiz ve idari personellerimize, dahili numaralarına erişebilirsiniz.\n\nİletişim Bilgileri\n\nTelefon:\n\n+90 (212) 533 65 32\n\nFax:\n\n+90 (212) 631\n                            91 50\n\nE-Posta:\n\n[email protected]\n\nAdres:\n\nCibali Mah. Kadir\n                            Has Cad. 34083 Fatih, İstanbul",
  "language": "tr",
  "content_type": "academic",
  "timestamp": "2026-04-12T18:45:13.951841Z",
  "university": "Kadir Has University",
  "source_hash": "85ca17a183af363c7b70d29ff44ab94d8ae924cd5cd63ae902f98c3de70b562d"
}