{
  "title": "Hemşirelik Bölümü - Ders İçeriği",
  "url": "https://www.esenyurt.edu.tr/icerik/1647-hemsirelik-bolumu-ders-icerigi",
  "content": "BİRİNCİ YARIYIL\n\n2312G1003 Mikrobiyoloji (2- 0),  2, 3 AKTS\n\nTıbbi Mikrobiyoloji, Asepsi, Antisepsi, Dezenfeksiyon, Sterilizasyon Kavramları, Bakteriyoloji, Viroloji, İmmünoloji, Mikoloji, Parazitoloji, Helmintoloji, Protozooloji, Arthropodoloji, Mikrobiyolojik Tanı Testleri\n\n23G1001 Fizyoloji (2- 0) , 2, 4 AKTS\n\n23G1005 Anatomi (3-0),3, 7 AKTS\n\nİKİNCİ YARIYIL\n\n2312B1006 Psikoloji (2-0-0-2/2)\n\nÜÇÜNCÜ YARIYIL\n\nDÖRDÜNCÜ YARIYIL\n\nBEŞİNCİ YARIYIL\n\nALTINCI YARIYIL\n\nYEDİNCİ YARIYIL\n\nSEKİZİNCİ YARIYIL\n\n2312B4004 Ürojinekoloji Hemşireliği (2-0), 2, 5 AKTS",
  "language": "en",
  "content_type": "academic",
  "timestamp": "2026-04-12T18:50:09.005707Z",
  "university": "Istanbul Esenyurt University",
  "source_hash": "fb011a8eaf56286fdfa2f2c60ab2662bd8e4ac918eff60b339776d93e200cd06"
}