{
  "title": "Kamuoyu Açıklaması",
  "url": "https://www.istun.edu.tr/en/announcements/kamuoyu-aciklamasi",
  "content": "Kamuoyu Açıklaması\n\nKAMUOYU AÇIKLAMASI\n\nPerşembe\n\nLeave Message\n\nAsk Us!\n\nBize Sorun!\n\n* Gerekli\n\n* Gerekli\n\n* Gerekli\n\n* Opsiyonel\n\nGönder\n\nKapat",
  "language": "en",
  "content_type": "news",
  "timestamp": "2026-04-12T18:23:07.401806Z",
  "university": "Istanbul Health and Technology University",
  "source_hash": "19fb588de0753ffa4b7632805b97e71b479c452c1ad3fc30b46cb989a4b4f297"
}