{
  "title": "Pisa Üniversitesi İle Erasmus Anlaşması",
  "url": "https://www.29mayis.edu.tr/tr/haber/pisa-universitesi-ile-erasmus-anlasmasi",
  "content": "www.unipi.it\n\nGörüntülenme:\n\n902\n\nYayınlanma Tarihi:\n\n26 Ekim 2017\n\nWebmail\n\nAkademik Bilgi Sistemi\n\nAday Öğrenci\n\nRehber\n\nPortal\n\nİHALELER",
  "language": "en",
  "content_type": "news",
  "timestamp": "2026-04-12T19:02:50.901825Z",
  "university": "Istanbul 29 Mayıs University",
  "source_hash": "a784a07370a724bc26d6e5046ee491c92854c2f84217263d04050534383e38a3"
}