{
  "title": "İnsan ve Toplum Bilimleri Fakültesi Fakülte Yönetimi",
  "url": "https://www.uskudar.edu.tr/itbf/fakulte-yonetimi",
  "content": "Prof.Dr.\n\nBurcu CEYLAN\n\nÇağlar ŞENTÜRK\n\nPaylaş\n\nOluşturulma Tarihi\n\n:\n\nSizi Arayalım\n\nPhone\n\nokudum, onayladım.\n\nFormu Gönder",
  "language": "en",
  "content_type": "academic",
  "timestamp": "2026-04-12T23:01:06.188760Z",
  "university": "Üsküdar University",
  "source_hash": "dc2fd2f4ad0d7ffd1159ee7a9b9079c8046e21c6599033a1ff04b10f179327b0"
}