{
  "title": "Fakülte Semineri: “Dijital Çağda Siber Güvenlik”",
  "url": "https://www.uskudar.edu.tr/duyuru/fakulte-semineri-dijital-cagda-siber-guvenlik/7784",
  "content": "Etkinliğin Konusu:\n\nEtkinliğin Konuşmacıları:\n\nÖmer Yerlikaya\n\n11.03.2026, 13.00\n\nEtkinliğin Yeri:\n\nSokrates Salonu\n\nPaylaş\n\nOluşturulma Tarihi\n\n:\n\n10 Mart 2026\n\nSizi Arayalım\n\nPhone\n\nokudum, onayladım.\n\nFormu Gönder",
  "language": "en",
  "content_type": "news",
  "timestamp": "2026-04-12T23:03:33.968269Z",
  "university": "Üsküdar University",
  "source_hash": "556a95e635415691164472536a7910194a5b65dcb801d7d859516b51772742f7"
}