{
  "title": "You Are Invited to the \"Visualization and Animation\" Event!",
  "url": "https://www.uskudar.edu.tr/en/announcement/you-are-invited-to-the-visualization-and-animation-event/6700",
  "content": "You Are Invited to the \"Visualization and Animation\" Event!\n\nJoin us at the\n\nVisualization and Animation\n\nevent!\n\nThis event, organized by the Department of Cartoon and Animation in collaboration with Digital Panorama Advertising Agency, welcomes all Faculty of Communication students.\n\nDate\n\n: Wednesday, November 6, 2024\n\nTime\n\nLocation\n\n: Fuat Sezgin Conference Hall, 1st basement floor, Block C, South Campus.\n\nSpeakers from Digital Panorama Advertising Agency, including Kaan Azov, Zehra Alkan, and Teberdar Gürbey, will share insights. The session will be moderated by Lecturer Özgül Öztürk from the Department of Cartoon and Animation.\n\nAs a part of the\n\nUniversity Culture\n\ncourse, this event\n\nwill feature discussions on industry trends, workflows, different business models, and career roadmaps in the fields of visualization and animation. We look forward to seeing you there on Wednesday at 11:00 a.m.!\n\nShare\n\nCreation Date\n\n:\n\nPhone\n\nI have read and agree to the\n\nPrivacy and Disclosure Notice\n\nunder the Personal Data Protection Law.\n\nSubmit Form",
  "language": "en",
  "content_type": "news",
  "timestamp": "2026-04-12T23:10:17.371652Z",
  "university": "Üsküdar University",
  "source_hash": "e63a6c361f285017dcfd2d191ba7c1f63eb8737eb433e8116c023b6ca4c7b9db"
}