{
  "title": "2547 Sayılı Kanunun 44 (c) Maddesi Uygulama Esasları Hakkında",
  "url": "https://www.beykent.edu.tr/duyurular/detay/2547-sayili-kanunun-44-c-maddesi-uygulama-esaslari-hakkinda",
  "content": "Tarih: 24 Ocak 2022\n\n2547 Sayılı Kanunun 44 (c) Maddesi Uygulama Esasları Hakkında\n\nBu uygulama esasları; 2547 sayılı kanunun 44. Maddesinin (c) fıkrası ile Beykent Üniversitesi Ön lisans ve Lisans Eğitim Öğretim Yönetmeliği hükümleri doğrultusunda azami öğrenim sürelerini dolduran son sınıf öğrencilerine ilişkin olarak yapılacak işlemleri kapsar.\n\nDetaylı bilgi için tıklayınız.\n\nFacebook'ta Paylaş\n\nTwitter'da Paylaş\n\nLinkedIn'de Paylaş\n\nE-posta Gönder\n\nWhatsapp'ta Paylaş\n\nDuyurular\n\nArşiv\n\nCOVID-19\n\nDuyurular\n\nİhaleler\n\nKütüphane\n\nLisansüstü\n\nPasif İhaleler\n\nStaj\n\nTTO\n\nYabancı Dil Hazırlık\n\nSitemizden en iyi şekilde faydalanabilmeniz için, amacımızla sınırlı ve geçildiği uygun şekilde ve size iletişimiz analiz etmek için çerez kullanıyoruz. \n\t\t\t\t\t\tÇerezlerin nasıl kullandığımızı incelemek ve çerezleri nasıl kontrol edebileceğinizi öğrenmek için\n\nÇerez Politikamızı\n\ninceleyebilirsiniz.\n\nKişiselleştir\n\nTümünü Reddet\n\nTümünü Kabul Et",
  "language": "tr",
  "content_type": "news",
  "timestamp": "2026-04-12T20:55:06.519027Z",
  "university": "Istanbul Beykent University",
  "source_hash": "4c59c8ff8ce0ea8589996f2347d361e7897b92e54c6a839ae742e71a6ea12da5"
}