{
  "title": "Duyurular",
  "url": "https://www.beykent.edu.tr/duyurular/duyurular/38",
  "content": "Duyurular\n\nAğu\n\n24\n\nÖğretim Görevlisi Ön Değerlendirme Sonucu Hk.\n\nAğu\n\n24\n\n2022-2023 Eğitim Öğretim Yılı Güz Dönemi Kurum İçi ve Kurum Dışı Ek Madde 1 ile Yatay Geçiş Hakkı Kazanan Öğrenciler\n\nAğu\n\n23\n\nAraştırma Görevlisi Ön Değerlendirme Sonucu Hk.\n\nAğu\n\n21\n\nÜniversitemize 17 Öğretim Üyesi (Profesör, Doçent, Doktor Öğretim Üyesi) Alınacaktır\n\nAğu\n\n21\n\nÜniversitemize 3 Öğretim Görevlisi ve 2 Araştırma Görevlisi Alınacaktır\n\nAğu\n\n18\n\n2022-2023 Eğitim Öğretim Yılı Güz Dönemi Başarı Ortalaması ile Kurumlar Arası Yurt İçi Yatay Geçiş Sonuçları\n\nAğu\n\n12\n\nÜniversitemize 2 Öğretim Üyesi(Doktor Öğretim Üyesi) Alınacaktır.\n\nAğu\n\n12\n\nÜniversitemize 7 Öğretim Elemanı Alınacaktır.\n\nAğu\n\n09\n\n7417 Sayılı Kanunla Düzenlenen Öğrenci Affı Hakkında\n\nAğu\n\n09\n\nÜniversitemize 12 Öğretim Görevlisi Alınacaktır\n\nAğu\n\n07\n\nÜniversitemize 17 Öğretim Üyesi Alınacaktır\n\nAğu\n\n07\n\nÜniversitemize 4 Araştırma Görevlisi Alınacaktır\n\nTem\n\n29\n\nÖğretim Görevlisi ve Araştırma Görevlisi Bilim Sınavı Sonucu\n\nTem\n\n26\n\nÖğretim Görevlisi ve Araştırma Görevlisi Ön Değerlendirme Sonucu\n\nTem\n\n25\n\n2021-2022 Eğitim-Öğretim Yılı Yaz Öğretiminde Açılan Dersler Hakkında\n\nTem\n\n24\n\nAraştırma Görevlisi Alınacaktır\n\nTem\n\n24\n\nÜniversitemize 2 Öğretim Üyesi (Doktor Öğretim Üyesi) Alınacaktır.\n\nTem\n\n21\n\n2022-2023 Eğitim-Öğretim Yılı Özel Yetenek Sınavı Başvuru Şartları\n\nTem\n\n19\n\n2021-2022 Eğitim-Öğretim Yılı Yaz Öğretimi Ders Kayıtları Hakkında\n\nTem\n\n07\n\nYabancı Diller Yüksekokulu İngilizce Hazırlık Programı 2021-2022 Eğitim-Öğretim Yaz Dönemi BULET  (Yabancı Dilde Yeterlik Sınavı)  Sonuçlanmıştır.\n\n«\n\n31\n\n32\n\n33\n\n34\n\n35\n\n36\n\n37\n\n38\n\n(current)\n\n39\n\n40\n\n»\n\nSitemizden en iyi şekilde faydalanabilmeniz için, amacımızla sınırlı ve geçildiği uygun şekilde ve size iletişimiz analiz etmek için çerez kullanıyoruz. \n\t\t\t\t\t\tÇerezlerin nasıl kullandığımızı incelemek ve çerezleri nasıl kontrol edebileceğinizi öğrenmek için\n\nÇerez Politikamızı\n\ninceleyebilirsiniz.\n\nKişiselleştir\n\nTümünü Reddet\n\nTümünü Kabul Et",
  "language": "tr",
  "content_type": "news",
  "timestamp": "2026-04-12T20:38:04.987851Z",
  "university": "Istanbul Beykent University",
  "source_hash": "04744b64e39cd6b2598cbb79b82fca6dab8a64ed427eb77ea07fb7847104aa9d"
}