{
  "title": "2020-2021 Erasmus+ Programı Başvuruları Hakkında Duyuru",
  "url": "https://www.beykent.edu.tr/duyurular/detay/2020-2021-erasmus-programi-basvurulari-hakkinda-duyuru",
  "content": "2020-2021 Erasmus+ Programı Başvuruları Hakkında Duyuru\n\nDeğerli Öğrencilerimiz,\n\nErasmus+ Projesi’nin 2021-2027 yıllarını kapsayan, yeni döneminin taslağını çizen Program Rehberi Avrupa Birliği Komisyonu tarafından geçtiğimiz günlerde yayınlanmıştır.\n\nYeni proje ile birlikte önümüzdeki dönem faaliyetleri Türkiye Ulusal Ajansı’nın yayınlayacağı uyarlanmış el kitabındaki kurallara göre gerçekleşecektir. Uyarlanmış el kitabı ve\n\nyeni dönem başvuru şart ve koşulları kesinleştiğinde\n\nBeykent Üniversitesi’nde 2021 Erasmus+ başvuru süreci başlatılacaktır.\n\nTürkiye Ulusal Ajansı üniversitemizin de dahil olduğu yükseköğretim kurumlarıyla 2021 proje dönemine ilişkin aşağıdaki bilgileri paylaşmıştır:\n\n‘’2021 sözleşme yılı için en erken proje başlangıç tarihinin 01 Eylül 2021 olması beklenmektedir. Dolayısıyla 2021 sözleşmesi kapsamında tahsis edilecek hibeler bakımından bu tarihten önce staj, öğrenim ve personel hareketliliği için faaliyet başlangıç tarihi belirlenmesi mümkün değildir.’’\n\nTürkiye Ulusal Ajansı tarafından bildirilen tebliğ metni aşağıdaki gibidir:\n\n“Bilindiği gibi 1 Ocak 2021 tarihi itibarıyla yeni Erasmus+ Programı başlamıştır. 2021 sözleşme yılı için kurallarda ve hibe miktarlarında değişiklik beklenmektedir. Söz konusu kurallar kesinleştiğinde hak edilen hibe miktarlarında ve  hareketlilik sürelerinde  değişiklik olabileceği gibi kazanılan hakkın yitirilmesi de söz konusu olabilir. Diğer taraftan,  Türkiye ile Avrupa Birliği arasında 2021-2027 yeni Erasmus+ programına katılım anlaşması ile 2021 Yılı Delegasyon Anlaşması henüz imzalanmamıştır. Söz konusu anlaşma süreçlerinde yaşanacak gecikmelerden veya aksaklıklardan kaynaklanabilecek  maddi veya manevi kayıplardan  kurumumuz ve Türkiye Ulusal Ajansı sorumlu tutulamaz.”\n\nSüreç ile ilgili tüm duyuru ve güncel bilgileri web sitemiz ve sosyal medya hesaplarımız üzerinden takip edebilirsiniz.\n\nSosyal medya hesaplarımız:\n\nInstagram:\n\n@internationaloffice\n\nInstagram:\n\n@beykenterasmus\n\nFacebook:\n\nBeykent Üniversitesi Uluslararası Ofisi\n\nTwitter:\n\n@beykentint\n\nBaşarılı bir öğretim yılı dileklerimizle\n\nBeykent Üniversitesi\n\nUluslararası Etkinlikler Daire Başkanlığı\n\nFacebook'ta Paylaş\n\nTwitter'da Paylaş\n\nLinkedIn'de Paylaş\n\nE-posta Gönder\n\nWhatsapp'ta Paylaş\n\nDuyurular\n\nArşiv\n\nCOVID-19\n\nDuyurular\n\nİhaleler\n\nKütüphane\n\nLisansüstü\n\nPasif İhaleler\n\nStaj\n\nTTO\n\nYabancı Dil Hazırlık\n\nSitemizden en iyi şekilde faydalanabilmeniz için, amacımızla sınırlı ve geçildiği uygun şekilde ve size iletişimiz analiz etmek için çerez kullanıyoruz. \n\t\t\t\t\t\tÇerezlerin nasıl kullandığımızı incelemek ve çerezleri nasıl kontrol edebileceğinizi öğrenmek için\n\nÇerez Politikamızı\n\ninceleyebilirsiniz.\n\nKişiselleştir\n\nTümünü Reddet\n\nTümünü Kabul Et",
  "language": "tr",
  "content_type": "news",
  "timestamp": "2026-04-12T20:55:39.998996Z",
  "university": "Istanbul Beykent University",
  "source_hash": "1078b86b19ddd3b0bdb139a4bf6024c596e6af0a0e77f229c0c25e402849c91e"
}