{
  "title": "Doğuş Üniversitesi Catering Hizmeti İhalesi",
  "url": "https://www.dogus.edu.tr/ihaleler/detay/dogus-universitesi-catering-hizmeti-ihalesi",
  "content": "İhaleler\n\nDetay\n\nDoğuş Üniversitesi\n\niçin y\n\na\n\nİhale Tarihi\n\n: 16.02.2017 Perşembe Saat 13:00\n\nWeb :\n\nwww.dogus.edu.tr\n\nPaylaş\n\nShare to Whatsapp\n\nShare to Twitter\n\nShare to Facebook\n\nShare to LinkedIn",
  "language": "en",
  "content_type": "academic",
  "timestamp": "2026-04-12T21:51:22.844359Z",
  "university": "Doğuş University",
  "source_hash": "7f6ebe81ec04ed5fe7e027424f356e3ea3a7590376c41e3004a372003a69d505"
}