{
  "title": "Haberler",
  "url": "https://www.dogus.edu.tr/ogrenci/haberler/27",
  "content": "Öğrenci\n\nHaberler\n\nKategoriler\n\nGüncel\n\nBilim-Teknoloji\n\nKültür-Sanat\n\nSpor-Sağlık\n\nOrganizasyonlar\n\nArşiv\n\n«\n\n21\n\n22\n\n23\n\n24\n\n25\n\n26\n\n27\n\n(current)\n\n28\n\n29",
  "language": "en",
  "content_type": "news",
  "timestamp": "2026-04-12T21:41:18.610284Z",
  "university": "Doğuş University",
  "source_hash": "8b554f198ef7440400a60efadc142f078dc8e866e946a5749d6d63df8a2da879"
}