{
  "title": "Anasayfa | Sanat Tasarım Fakültesi",
  "url": "https://www.dogus.edu.tr/akademik/fakulteler/sanat-ve-tasarim-fakultesi",
  "content": "Dekanın  Mesajı\n\nProf. Dr. Kamil USLU\n\nDekan\n\nEndüstriyel Tasarım\n\nGrafik\n\nGrafik (İngilizce)\n\nİç Mimarlık\n\nMimarlık\n\nOyunculuk\n\nDevamını Oku\n\nDevamını Oku\n\nDevamını Oku\n\nDevamını Oku\n\nDevamını Oku\n\nDevamını Oku\n\nDevamını Oku\n\nDevamını Oku\n\nDevamını Oku\n\nDevamını Oku\n\nDevamını Oku\n\n33. KOZA GENÇ MODA TASARIMCILARI YARIŞMASI\n\nDevamını Oku\n\nDevamını Oku\n\nCookie Workshop\n\nDevamını Oku\n\nDevamını Oku\n\nGastrosanat Bursa'da\n\nDevamını Oku\n\nDevamını Oku\n\nDevamını Oku\n\nDevamını Oku\n\nDevamını Oku\n\nAkademik Çalışmalar\n\nDetay\n\nDetay\n\nDetay\n\nDetay\n\nDetay\n\nDetay\n\nDetay\n\nDetay\n\nDetay",
  "language": "en",
  "content_type": "academic",
  "timestamp": "2026-04-12T21:17:57.804113Z",
  "university": "Doğuş University",
  "source_hash": "75fc1ca3780e9bbc1c623846a10c30e7c55f83ba5a2b6ac5856b2f2b6afbed9d"
}