{
  "title": "İstanbul Okan Üniversitesi",
  "url": "https://www.okan.edu.tr/cv/begum-turkyilmaz/",
  "content": "Begüm Türkyılmaz\n\nMENU\n\nBegüm Türkyılmaz\n\ne.\n\nt.\n\n0 (216) 677 16 30 #3512\n\nBegüm Türkyılmaz\n\nGörevleri\n\nBulunduğu Kampüs\n\nTuzla Kampüsü\n\nBulunduğu Bina\n\nYaşam Merkezi\n\nBölüm\n\nİdari Kadro\n\nSpor Müdürlüğü\n\nGörevi\n\nen\n\ntr",
  "language": "en",
  "content_type": "academic",
  "timestamp": "2026-04-12T19:30:42.934426Z",
  "university": "Istanbul Okan University",
  "source_hash": "4341e7681618c4298a94bce5cfbbc5b87d0b462b7c2c31b207a31564e0411240"
}