{
  "title": "Diş Hekimliği Fakültesi",
  "url": "https://www.okan.edu.tr/dis/sayfa/7232/1-sinif-ders-konu-basliklari/",
  "content": "Okan Anasayfa\n\nEğitim\n\nAkademik Birimler\n\nFakülteler\n\nAkademik Program\n\n1. Sınıf\n\nMENU\n\nDHF107 Biyofizik\n\nDHF119 Protetik Diş Tedavisi I (Teorik)\n\nen\n\ntr",
  "language": "en",
  "content_type": "academic",
  "timestamp": "2026-04-12T19:26:27.504239Z",
  "university": "Istanbul Okan University",
  "source_hash": "6377112c39a6b5de92da74d1e323d8a472479ba21af693da726bd84b4dca1d44"
}