{
  "title": "İstanbul Okan University",
  "url": "https://www.okan.edu.tr/en/page/8398/english-academic-writing-skills-development-unit/",
  "content": "English Academic Writing Skills Development Unit\n\nOkan Homepage\n\nEducation\n\nAcademic Units\n\nUnits under Rectorate\n\nForeign Languages ​​Department\n\nDepartments\n\nWriting Skills Enhancement\n\nMENU\n\nEnglish Academic Writing Skills Development Unit\n\nThe English Academic Writing Skills Development Unit is a department that provides support to students in enhancing their writing skills and meeting academic writing requirements through individual counseling, writing workshops, and classes.\n\nWriting Education:\n\nThey offer students instruction on fundamental writing rules, style, organization, and referencing. They also provide knowledge about academic writing types and formats.\n\nOriginality and Plagiarism Control:\n\nThey offer various tools and methods to ensure that students' written content is original and plagiarism-free. They raise awareness about plagiarism and teach proper citation and referencing practices.\n\nLanguage and Grammar Support:\n\nThey assist students who are learning English as a foreign language in grammar, spelling, and language usage.\n\nAcademic Writing Guides and Resources:\n\nThey provide students with guides, sample articles, resources, and recommendations related to academic writing. These resources facilitate the writing process for students.\n\nAssessment and Feedback:\n\nThey evaluate students' written texts and provide feedback. This feedback helps students enhance their writing skills.\n\nDevelopment of Educational Materials:\n\nThey create relevant course materials and writing resources, guiding students to improve their writing skills.\n\nThis unit aids students in improving their writing skills, thereby enhancing their academic success and strengthening their effective communication abilities.\n\nen\n\ntr",
  "language": "en",
  "content_type": "academic",
  "timestamp": "2026-04-12T19:26:38.296746Z",
  "university": "Istanbul Okan University",
  "source_hash": "7d1188c2b5ece099cf0b1a8ef3ecc7a0e20609179ad8395a0a8b3d0f2182a464"
}