{
  "title": "Mühendislik ve Doğa Bilimleri Fakültesi",
  "url": "https://www.okan.edu.tr/muhendislik/sayfa/9643/ergonomi-laboratuvari/",
  "content": "Ergonomi Laboratuvarı\n\nOkan Anasayfa\n\nEğitim\n\nAkademik Birimler\n\nFakülteler\n\nBölümler\n\nOtomotiv Mühendisliği\n\nLaboratuvarlar\n\nErgonomi Laboratuvarı\n\nMENU\n\nen\n\ntr",
  "language": "en",
  "content_type": "academic",
  "timestamp": "2026-04-12T19:24:23.721404Z",
  "university": "Istanbul Okan University",
  "source_hash": "2882c50ca649825d066fb123ff37576aa390c023079370b73293cf24552d6a67"
}